chatnio/__init__.py
chatnio/auth.py
chatnio/chat.py
chatnio/conversation.py
chatnio/globals.py
chatnio/quota.py
chatnio-0.1.4.dist-info/AUTHORS.rst
chatnio-0.1.4.dist-info/LICENSE
chatnio-0.1.4.dist-info/METADATA
chatnio-0.1.4.dist-info/WHEEL
chatnio-0.1.4.dist-info/top_level.txt
chatnio-0.1.4.dist-info/RECORD
